<?xml version="1.0" encoding="utf-8" ?>
<dwsync>
<file name="autofill.js" server="37.187.132.45//morbiflex/" local="132564124130000000" remote="132878443200000000" Dst="1" />
<file name="buttons.js" server="37.187.132.45//morbiflex/" local="132586450870000000" remote="132878443200000000" Dst="1" />
<file name="column-reorder.js" server="37.187.132.45//morbiflex/" local="132564124650000000" remote="132878443200000000" Dst="1" />
<file name="fixed-header.js" server="37.187.132.45//morbiflex/" local="132564124720000000" remote="132878443200000000" Dst="1" />
<file name="key-table.js" server="37.187.132.45//morbiflex/" local="132564124750000000" remote="132878443200000000" Dst="1" />
<file name="fixed-column.js" server="37.187.132.45//morbiflex/" local="132564124690000000" remote="132878443200000000" Dst="1" />
<file name="row-group.js" server="37.187.132.45//morbiflex/" local="132564124780000000" remote="132878443200000000" Dst="1" />
<file name="row-reorder.js" server="37.187.132.45//morbiflex/" local="132564124820000000" remote="132878443200000000" Dst="1" />
<file name="scroller.js" server="37.187.132.45//morbiflex/" local="132564650460000000" remote="132878443200000000" Dst="1" />
<file name="select.js" server="37.187.132.45//morbiflex/" local="132564126180000000" remote="132878443200000000" Dst="1" />
<file name="search-panes.js" server="37.187.132.45//morbiflex/" local="132564126140000000" remote="132878443200000000" Dst="1" />
</dwsync>